qrcode_artistic.py
qrcode_artistic-3.0.2.dist-info/LICENSE
qrcode_artistic-3.0.2.dist-info/METADATA
qrcode_artistic-3.0.2.dist-info/WHEEL
qrcode_artistic-3.0.2.dist-info/entry_points.txt
qrcode_artistic-3.0.2.dist-info/top_level.txt
qrcode_artistic-3.0.2.dist-info/RECORD
