Metadata-Version: 2.1
Name: qrcode-artistic
Version: 3.0.2
Summary: Artistic (Micro) QR Code plugin for Segno
Author-email: Lars Heuer <heuer@semagia.com>
License: Copyright (c) 2016 - 2020, Lars Heuer
Project-URL: Homepage, https://github.com/heuer/qrcode-artistic/
Project-URL: Documentation, https://segno.readthedocs.io/en/latest/artistic-qrcodes.html
Project-URL: Repository, https://github.com/heuer/qrcode-artistic.git
Project-URL: Changelog, https://github.com/heuer/qrcode-artistic/blob/master/CHANGES.rst
Project-URL: Issue Tracker, https://github.com/heuer/qrcode-artistic/issues
Keywords: QR Code,Micro QR Code,ISO/IEC 18004,ISO/IEC 18004:2006(E),ISO/IEC 18004:2015(E),qrcode,QR,barcode,matrix,2D
Classifier: Development Status :: 4 - Beta
Classifier: Intended Audience :: Developers
Classifier: License :: OSI Approved :: BSD License
Classifier: Operating System :: OS Independent
Classifier: Programming Language :: Python
Classifier: Programming Language :: Python :: 3
Classifier: Programming Language :: Python :: 3.7
Classifier: Programming Language :: Python :: 3.8
Classifier: Programming Language :: Python :: 3.9
Classifier: Programming Language :: Python :: 3.10
Classifier: Programming Language :: Python :: 3.11
Classifier: Programming Language :: Python :: 3.12
Classifier: Topic :: Multimedia :: Graphics
Classifier: Topic :: Printing
Classifier: Topic :: Software Development :: Libraries :: Python Modules
Classifier: Topic :: Utilities
Requires-Python: >=3.5
License-File: LICENSE
Requires-Dist: segno>=1.0.2
Requires-Dist: Pillow
Provides-Extra: svg
Requires-Dist: cairosvg; extra == "svg"
